irods_avu_json-2.2.0.data/data/LICENSE.md/LICENSE.md
irods_avu_json-2.2.0.data/data/README.md/README.md
irods_avu_json-2.2.0.data/data/inputs/basic.json
irods_avu_json-2.2.0.data/data/inputs/empty-arrays.json
irods_avu_json-2.2.0.data/data/inputs/example.json
irods_avu_json-2.2.0.data/data/inputs/extended_example.json
irods_avu_json-2.2.0.data/data/inputs/nested-arrays.json
irods_avu_json-2.2.0.data/data/inputs/types.json
irods_avu_json-2.2.0.data/data/jsonavu/__init__.py
irods_avu_json-2.2.0.data/data/jsonavu/avu2json.py
irods_avu_json-2.2.0.data/data/jsonavu/json2avu.py
irods_avu_json-2.2.0.data/data/test/__init__.py
irods_avu_json-2.2.0.data/data/test/test_irods_avu_json.py
irods_avu_json-2.2.0.data/scripts/conversion.py
jsonavu/__init__.py
jsonavu/avu2json.py
jsonavu/json2avu.py
irods_avu_json-2.2.0.dist-info/LICENSE.md
irods_avu_json-2.2.0.dist-info/METADATA
irods_avu_json-2.2.0.dist-info/WHEEL
irods_avu_json-2.2.0.dist-info/top_level.txt
irods_avu_json-2.2.0.dist-info/RECORD
