Metadata-Version: 2.1
Name: irods-avu-json
Version: 2.2.0
Summary: Bidirectional conversion between JSON(-LD) and iRODS AVUs
Home-page: https://github.com/MaastrichtUniversity/irods_avu_json
Author: Maastricht University - DataHub
Author-email: datahub@maastrichtuniversity.nl
License: UNKNOWN
Platform: UNKNOWN
Classifier: Programming Language :: Python :: 2.7
Classifier: Programming Language :: Python :: 3
Classifier: Operating System :: OS Independent
Classifier: License :: OSI Approved :: Apache Software License
